itk/itkHigherOrderAccurateGradientmageFilterPython.py
itk/HigherOrderAccurateGradientPython.py
itk/itkHigherOrderAccurateDerivativeImageFilterPython.py
itk/_HigherOrderAccurateGradientPython.cpython-39-aarch64-linux-gnu.so
itk/Configuration/HigherOrderAccurateGradient_snake_case.py
itk/Configuration/HigherOrderAccurateGradientConfig.py
itk_higherorderaccurategradient.libs/libtbb-e046f41a.so.12.9
itk_higherorderaccurategradient-1.3.1.dist-info/RECORD
itk_higherorderaccurategradient-1.3.1.dist-info/METADATA
itk_higherorderaccurategradient-1.3.1.dist-info/WHEEL
itk_higherorderaccurategradient-1.3.1.dist-info/licenses/LICENSE
